ks_base/__init__.py
ks_base/annotation.py
ks_base/constant/__init__.py
ks_base/constant/content_type.py
ks_base/container.py
ks_base/context.py
ks_base/entity.py
ks_base/ks_framework.py
ks_base/utils/__init__.py
ks_base/utils/collection_util.py
ks_base/utils/date_util.py
ks_base/utils/object_util.py
ks_base/utils/simple_util.py
ks_base-1.1.1.dist-info/METADATA
ks_base-1.1.1.dist-info/WHEEL
ks_base-1.1.1.dist-info/RECORD
