Metadata-Version: 2.1
Name: ks_base
Version: 1.1.1
Summary: 66666
Author: zz_lf
Author-email: 787036156@qq.com
Requires-Python: >=3.11,<4.0
Classifier: Programming Language :: Python :: 3
Classifier: Programming Language :: Python :: 3.11
Requires-Dist: flask (==2.3.2)
Requires-Dist: python-dateutil (==2.8.2)
